{
    "step": "F",
    "step_name": "Download and inspect the selected dataset",
    "dataset_name": "UCI Student Performance Dataset",
    "dataset_downloaded": true,
    "dataset_extracted": true,
    "math_file_found": true,
    "portuguese_file_found": true,
    "math_shape": [
        395,
        33
    ],
    "portuguese_shape": [
        649,
        33
    ],
    "same_columns": true,
    "inspection_report_created": true,
    "metadata_created": true,
    "column_check_created": true,
    "dtype_summary_created": true,
    "missing_summary_created": true,
    "duplicate_summary_created": true,
    "target_summary_created": true,
    "variable_type_summary_created": true,
    "descriptive_summaries_created": true,
    "preview_files_created": true,
    "completed": true,
    "completed_at": "2026-06-27 20:28:29"
}